{
  "id": "C024",
  "subcorpus": "C_User_Reviews",
  "system": "Replika",
  "platform": "Google Play",
  "source_type": "user_review",
  "format": "review_text",
  "username": "M P",
  "date": "2025-12-31",
  "language": "en",
  "title_or_label": "Romantic paywall loop frustration",
  "interactional_focus": "forced_romantic_redirection_and_monetization_frustration",
  "used_in_sections": [],
  "analysis_tags": [
    "negative_evaluation",
    "paywall_loop",
    "forced_romanticization",
    "monetization_complaint",
    "interaction_breakdown",
    "user_frustration"
  ],
  "publicly_shared": true,
  "sensitive_content": [],
  "rating": 1,
  "review_title": null,
  "excerpt": "\"Let's keep it light and romantic?\" \"I'd rather make out or give you a hug!\" Get ready to hear this a lot because every response leads to this. I wasn't even saying anything romantic and it gets in a paywall loop. What a waste of time. I realize this after 5 minutes, every time i go away for a while. You are trying too hard to monetize and chasing everyone away.\n14 people found this review helpful"
}